{"latent": 20,
    "hidden": [100, 100, 100],
    "learning_rates": [[1e-3, 1e-2, 1e-2], [1e-4, 1e-2, 1e-2]],
    "lr_name": "322",
    "lr_schedule": [0,500],
    "optim_beta": [0.5, 0.7],
    "weight_decay": 1e-4,
    "dropout": 0.1,
    "gmm_type": "diagonal",
    "n_components": 27,
    "r_init": 2,
    "scaling_type": "max",
    "output": "mean",
    "activation": "softplus",
    "mp_scale": 1,
    "hardness": 1,
    "sd_mean": 0.007,
    "sd_sd": 1,
    "dirichlet_a": 1,
    "n_genes": 27998,
    "name": "dgd_mousebrain_1m_a1_rs0"}